MANIFEST.in
README.rst
setup.py
bin/et
bin/et.cmd
et_cli.egg-info/PKG-INFO
et_cli.egg-info/SOURCES.txt
et_cli.egg-info/dependency_links.txt
et_cli.egg-info/requires.txt
et_cli.egg-info/top_level.txt
etcli/__init__.py
etcli/app.py
etcli/commands.py
etcli/et_objects.py