Metadata-Version: 1.0
Name: et-cli
Version: 0.0.7
Summary: ExactTarget CLI Tool
Home-page: https://github.com/tzmfreedom/et-cli
Author: makoto tajitsu
Author-email: makoto_tajitsu@hotmail.co.jp
License: MIT
Platform: UNKNOWN
